AUTHORS.rst
CHANGELOG.rst
COPYING
MANIFEST.in
README.rst
requirements.txt
setup.py
django_terms.egg-info/PKG-INFO
django_terms.egg-info/SOURCES.txt
django_terms.egg-info/dependency_links.txt
django_terms.egg-info/not-zip-safe
django_terms.egg-info/requires.txt
django_terms.egg-info/top_level.txt
terms/__init__.py
terms/admin.py
terms/cms_app.py
terms/cms_plugin_processors.py
terms/cms_plugins.py
terms/forms.py
terms/html.py
terms/managers.py
terms/menu.py
terms/middleware.py
terms/models.py
terms/search_indexes.py
terms/settings.py
terms/sitemaps.py
terms/urls.py
terms/views.py
terms/locale/en/LC_MESSAGES/django.mo
terms/locale/en/LC_MESSAGES/django.po
terms/locale/fr/LC_MESSAGES/django.mo
terms/locale/fr/LC_MESSAGES/django.po
terms/locale/pt_BR/LC_MESSAGES/django.mo
terms/locale/pt_BR/LC_MESSAGES/django.po
terms/south_migrations/0001_initial.py
terms/south_migrations/0002_auto__chg_field_term_url.py
terms/south_migrations/0003_auto__chg_field_term_url.py
terms/south_migrations/0004_auto__add_field_term_case_sensitive.py
terms/south_migrations/__init__.py
terms/templates/glossary_plugin.html
terms/templates/search/indexes/terms/term_text.txt
terms/templates/terms/term_detail.html
terms/templates/terms/term_replace.html
terms/templatetags/__init__.py
terms/templatetags/terms.py
terms/tests/__init__.py
terms/tests/html/__init__.py
terms/tests/html/invalid_html.py
terms/tests/html/missing_end_tag.html
terms/tests/html/missing_start_tag.html
terms/tests/html/valid.html
terms/tests/html/valid_html.html
terms/tests/html/valid_html.py
terms/tests/html/valid_html_with_extra_spaces.html
terms/tests/terms/1_after.html
terms/tests/terms/1_before.html
terms/tests/terms/2_after.html
terms/tests/terms/2_before.html
terms/tests/terms/3_after.html
terms/tests/terms/3_before.html
terms/tests/terms/4_after.html
terms/tests/terms/4_before.html
terms/tests/terms/5_after1.html
terms/tests/terms/5_after2.html
terms/tests/terms/5_before.html
terms/tests/terms/6_after.html
terms/tests/terms/6_before.html
terms/tests/terms/__init__.py
terms/tests/terms/performance_test.json
terms/tests/terms/performance_test_after.html
terms/tests/terms/performance_test_before.html